deeplib/__init__.py
deeplib/datasets/__init__.py
deeplib/datasets/anomaly.py
deeplib/datasets/base.py
deeplib/datasets/coco.py
deeplib/datasets/detection.py
deeplib/datasets/segmentation.py
deeplib/loggers/__init__.py
deeplib/loggers/base.py
deeplib/loggers/mlflow.py
deeplib/loggers/tensorboard.py
deeplib/loggers/wandb.py
deeplib/metrics/__init__.py
deeplib/metrics/segmentation.py
deeplib/trainers/__init__.py
deeplib/trainers/base.py
deeplib/trainers/segmentation.py
deeplib-1.1.0.dist-info/LICENSE.md
deeplib-1.1.0.dist-info/METADATA
deeplib-1.1.0.dist-info/WHEEL
deeplib-1.1.0.dist-info/top_level.txt
deeplib-1.1.0.dist-info/RECORD
