Metadata-Version: 2.1
Name: deeplib
Version: 1.1.0
Summary: A deep learning library for computer vision tasks (CUDA ≥11.8 compatible)
Home-page: https://github.com/jonleinena/deeplib
Author: Jon Leiñena
Author-email: leinenajon@gmail.com
Classifier: Development Status :: 4 - Beta
Classifier: Intended Audience :: Developers
Classifier: Intended Audience :: Science/Research
Classifier: License :: OSI Approved :: MIT License
Classifier: Programming Language :: Python :: 3
Classifier: Programming Language :: Python :: 3.10
Classifier: Programming Language :: Python :: 3.11
Classifier: Topic :: Scientific/Engineering :: Artificial Intelligence
Classifier: Environment :: GPU :: NVIDIA CUDA
Requires-Python: >=3.10
License-File: LICENSE.md
Requires-Dist: albumentations==1.4.18
Requires-Dist: numpy
Requires-Dist: opencv-python-headless
Requires-Dist: PyYAML
Requires-Dist: tqdm
Requires-Dist: matplotlib
Requires-Dist: pytest>=7.0.0
Requires-Dist: black>=22.0.0
Requires-Dist: isort>=5.0.0
Requires-Dist: flake8>=4.0.0
Requires-Dist: tensorboard>=2.15.0
Requires-Dist: mlflow>=2.9.0
Requires-Dist: wandb>=0.16.0
Provides-Extra: core
Requires-Dist: albumentations==1.4.18; extra == "core"
Requires-Dist: numpy; extra == "core"
Requires-Dist: opencv-python-headless; extra == "core"
Requires-Dist: PyYAML; extra == "core"
Requires-Dist: tqdm; extra == "core"
Requires-Dist: matplotlib; extra == "core"
Requires-Dist: pytest>=7.0.0; extra == "core"
Requires-Dist: black>=22.0.0; extra == "core"
Requires-Dist: isort>=5.0.0; extra == "core"
Requires-Dist: flake8>=4.0.0; extra == "core"
Provides-Extra: all
Requires-Dist: albumentations==1.4.18; extra == "all"
Requires-Dist: numpy; extra == "all"
Requires-Dist: opencv-python-headless; extra == "all"
Requires-Dist: PyYAML; extra == "all"
Requires-Dist: tqdm; extra == "all"
Requires-Dist: matplotlib; extra == "all"
Requires-Dist: pytest>=7.0.0; extra == "all"
Requires-Dist: black>=22.0.0; extra == "all"
Requires-Dist: isort>=5.0.0; extra == "all"
Requires-Dist: flake8>=4.0.0; extra == "all"
Requires-Dist: tensorboard>=2.15.0; extra == "all"
Requires-Dist: mlflow>=2.9.0; extra == "all"
Requires-Dist: wandb>=0.16.0; extra == "all"
Provides-Extra: tensorboard
Requires-Dist: albumentations==1.4.18; extra == "tensorboard"
Requires-Dist: numpy; extra == "tensorboard"
Requires-Dist: opencv-python-headless; extra == "tensorboard"
Requires-Dist: PyYAML; extra == "tensorboard"
Requires-Dist: tqdm; extra == "tensorboard"
Requires-Dist: matplotlib; extra == "tensorboard"
Requires-Dist: pytest>=7.0.0; extra == "tensorboard"
Requires-Dist: black>=22.0.0; extra == "tensorboard"
Requires-Dist: isort>=5.0.0; extra == "tensorboard"
Requires-Dist: flake8>=4.0.0; extra == "tensorboard"
Requires-Dist: tensorboard>=2.15.0; extra == "tensorboard"
Provides-Extra: mlflow
Requires-Dist: albumentations==1.4.18; extra == "mlflow"
Requires-Dist: numpy; extra == "mlflow"
Requires-Dist: opencv-python-headless; extra == "mlflow"
Requires-Dist: PyYAML; extra == "mlflow"
Requires-Dist: tqdm; extra == "mlflow"
Requires-Dist: matplotlib; extra == "mlflow"
Requires-Dist: pytest>=7.0.0; extra == "mlflow"
Requires-Dist: black>=22.0.0; extra == "mlflow"
Requires-Dist: isort>=5.0.0; extra == "mlflow"
Requires-Dist: flake8>=4.0.0; extra == "mlflow"
Requires-Dist: mlflow>=2.9.0; extra == "mlflow"
Provides-Extra: wandb
Requires-Dist: albumentations==1.4.18; extra == "wandb"
Requires-Dist: numpy; extra == "wandb"
Requires-Dist: opencv-python-headless; extra == "wandb"
Requires-Dist: PyYAML; extra == "wandb"
Requires-Dist: tqdm; extra == "wandb"
Requires-Dist: matplotlib; extra == "wandb"
Requires-Dist: pytest>=7.0.0; extra == "wandb"
Requires-Dist: black>=22.0.0; extra == "wandb"
Requires-Dist: isort>=5.0.0; extra == "wandb"
Requires-Dist: flake8>=4.0.0; extra == "wandb"
Requires-Dist: wandb>=0.16.0; extra == "wandb"
